quirkshop_jlab3_react/__init__.py
quirkshop_jlab3_react/_version.py
quirkshop_jlab3_react/static/549.52da66ce04cc35505262.js
quirkshop_jlab3_react/static/568.5fce5471348b345f0453.js
quirkshop_jlab3_react/static/imports.css
quirkshop_jlab3_react/static/package.json
quirkshop_jlab3_react/static/remoteEntry.d1f8253c31ffaf3b6e13.js
quirkshop_jlab3_react-0.1.0.data/data/share/jupyter/labextensions/quirkshop-jlab3-react/549.52da66ce04cc35505262.js
quirkshop_jlab3_react-0.1.0.data/data/share/jupyter/labextensions/quirkshop-jlab3-react/568.5fce5471348b345f0453.js
quirkshop_jlab3_react-0.1.0.data/data/share/jupyter/labextensions/quirkshop-jlab3-react/imports.css
quirkshop_jlab3_react-0.1.0.data/data/share/jupyter/labextensions/quirkshop-jlab3-react/package.json
quirkshop_jlab3_react-0.1.0.data/data/share/jupyter/labextensions/quirkshop-jlab3-react/remoteEntry.d1f8253c31ffaf3b6e13.js
quirkshop_jlab3_react-0.1.0.dist-info/LICENSE
quirkshop_jlab3_react-0.1.0.dist-info/METADATA
quirkshop_jlab3_react-0.1.0.dist-info/WHEEL
quirkshop_jlab3_react-0.1.0.dist-info/top_level.txt
quirkshop_jlab3_react-0.1.0.dist-info/RECORD
