Metadata-Version: 2.1
Name: quirkshop-jlab3-react
Version: 0.1.0
Summary: Quirkshop JupyterLab3 React
Home-page: https://github.com/datalayer-jupyterlab/quirkshops
Author: Eric Charles
License: BSD-3-Clause
Keywords: jupyter,jupyterlab,jupyterlab3,extension
Platform: Linux
Platform: Mac OS X
Platform: Windows
Classifier: License :: OSI Approved :: BSD License
Classifier: Programming Language :: Python
Classifier: Programming Language :: Python :: 3
Classifier: Programming Language :: Python :: 3.6
Classifier: Programming Language :: Python :: 3.7
Classifier: Programming Language :: Python :: 3.8
Classifier: Framework :: Jupyter
Requires-Python: >=3.6
Requires-Dist: jupyterlab (==3.*,>=3.0.0rc2)
